pvi/__init__.py
pvi/__main__.py
pvi/_pv_group.py
pvi/_schema_utils.py
pvi/_version.py
pvi/_yaml_utils.py
pvi/device.py
pvi/py.typed
pvi/typed_model.py
pvi/utils.py
pvi/_convert/__init__.py
pvi/_convert/_asyn_convert.py
pvi/_convert/_parameters.py
pvi/_convert/_template_convert.py
pvi/_convert/utils.py
pvi/_format/__init__.py
pvi/_format/adl.py
pvi/_format/aps.adl
pvi/_format/aps.py
pvi/_format/base.py
pvi/_format/bob.py
pvi/_format/dls.bob
pvi/_format/dls.edl
pvi/_format/dls.py
pvi/_format/edl.py
pvi/_format/pvi.template.jinja
pvi/_format/screen.py
pvi/_format/template.py
pvi/_format/utils.py
pvi/_format/widget.py
pvi-0.12.0.dist-info/licenses/LICENSE
pvi-0.12.0.dist-info/METADATA
pvi-0.12.0.dist-info/WHEEL
pvi-0.12.0.dist-info/entry_points.txt
pvi-0.12.0.dist-info/top_level.txt
pvi-0.12.0.dist-info/RECORD
