Metadata-Version: 2.4
Name: pvi
Version: 0.12.0
Summary: EPICS PV Interface described in YAML
Author-email: Tom Cobb <tom.cobb@diamond.ac.uk>, Gary Yendell <gary.yendell@diamond.ac.uk>
License:                                  Apache License
Project-URL: GitHub, https://github.com/epics-containers/pvi
Classifier: Development Status :: 3 - Alpha
Classifier: License :: OSI Approved :: Apache Software License
Classifier: Programming Language :: Python :: 3.11
Classifier: Programming Language :: Python :: 3.12
Classifier: Programming Language :: Python :: 3.13
Requires-Python: >=3.11
License-File: LICENSE
Requires-Dist: pydantic>=2.7
Requires-Dist: lxml
Requires-Dist: lxml-stubs
Requires-Dist: ruamel.yaml
Requires-Dist: typer
Requires-Dist: jinja2
Provides-Extra: dev
Requires-Dist: copier; extra == "dev"
Requires-Dist: myst-parser; extra == "dev"
Requires-Dist: pipdeptree; extra == "dev"
Requires-Dist: pre-commit; extra == "dev"
Requires-Dist: pydata-sphinx-theme>=0.12; extra == "dev"
Requires-Dist: pyright; extra == "dev"
Requires-Dist: pytest; extra == "dev"
Requires-Dist: pytest-cov; extra == "dev"
Requires-Dist: pytest-markdown-docs; extra == "dev"
Requires-Dist: ruff; extra == "dev"
Requires-Dist: sphinx-autobuild; extra == "dev"
Requires-Dist: sphinx-copybutton; extra == "dev"
Requires-Dist: sphinx-design; extra == "dev"
Requires-Dist: sphinx-autodoc2; extra == "dev"
Requires-Dist: tox-direct; extra == "dev"
Requires-Dist: types-mock; extra == "dev"
Dynamic: license-file
